tektonbundle/__init__.py
tektonbundle/cli.py
tektonbundle/tektonbundle.py
tektonbundle-0.3.0.dist-info/AUTHORS.rst
tektonbundle-0.3.0.dist-info/LICENSE
tektonbundle-0.3.0.dist-info/METADATA
tektonbundle-0.3.0.dist-info/WHEEL
tektonbundle-0.3.0.dist-info/entry_points.txt
tektonbundle-0.3.0.dist-info/top_level.txt
tektonbundle-0.3.0.dist-info/RECORD
