Metadata-Version: 2.1
Name: tektonbundle
Version: 0.3.0
Summary: This willl take a bunch of tekton templates resource and compile it as a single entity, Pipelinerun.
Home-page: https://github.com/chmouel/tektonbundle
Author: Chmouel Boudjnah
Author-email: chmouel@chmouel.com
License: MIT license
Keywords: tektonbundle
Platform: UNKNOWN
Classifier: Development Status :: 2 - Pre-Alpha
Classifier: Intended Audience :: Developers
Classifier: License :: OSI Approved :: MIT License
Classifier: Natural Language :: English
Classifier: Programming Language :: Python :: 3
Classifier: Programming Language :: Python :: 3.5
Classifier: Programming Language :: Python :: 3.6
Classifier: Programming Language :: Python :: 3.7
Classifier: Programming Language :: Python :: 3.8
Requires-Python: >=3.5
